LICENSE
MANIFEST.in
README.md
pyproject.toml
setup.cfg
setup.py
src/pymgrid/MicrogridGenerator.py
src/pymgrid/__init__.py
src/pymgrid/version.py
src/pymgrid/_deprecated/__init__.py
src/pymgrid/_deprecated/non_modular_microgrid.py
src/pymgrid/_deprecated/Environments/Environment.py
src/pymgrid/_deprecated/Environments/Preprocessing.py
src/pymgrid/_deprecated/Environments/__init__.py
src/pymgrid/_deprecated/Environments/pymgrid_csca.py
src/pymgrid/_deprecated/Environments/pymgrid_csca_old.py
src/pymgrid/_deprecated/Environments/pymgrid_csda.py
src/pymgrid/_deprecated/Environments/pymgrid_cspla.py
src/pymgrid/algos/Control.py
src/pymgrid/algos/__init__.py
src/pymgrid/algos/mpc/__init__.py
src/pymgrid/algos/mpc/mpc.py
src/pymgrid/algos/priority_list/__init__.py
src/pymgrid/algos/priority_list/priority_list.py
src/pymgrid/algos/priority_list/priority_list_element.py
src/pymgrid/algos/rbc/__init__.py
src/pymgrid/algos/rbc/_nonmodular_rbc.py
src/pymgrid/algos/rbc/rbc.py
src/pymgrid/algos/saa/__init__.py
src/pymgrid/algos/saa/saa.py
src/pymgrid/convert/__init__.py
src/pymgrid/convert/conversion_test_sandbox.py
src/pymgrid/convert/convert.py
src/pymgrid/convert/get_module.py
src/pymgrid/convert/to_nonmodular_ops.py
src/pymgrid/data/.DS_Store
src/pymgrid/data/__init__.py
src/pymgrid/data/co2/__init__.py
src/pymgrid/data/co2/co2_caiso.csv
src/pymgrid/data/co2/co2_duke.csv
src/pymgrid/data/load/RefBldgFullServiceRestaurantNew2004_v1.3_7.1_6A_USA_MN_MINNEAPOLIS.csv
src/pymgrid/data/load/RefBldgHospitalNew2004_7.1_5.0_3C_USA_CA_SAN_FRANCISCO.csv
src/pymgrid/data/load/RefBldgLargeHotelNew2004_v1.3_7.1_4A_USA_MD_BALTIMORE.csv
src/pymgrid/data/load/RefBldgLargeOfficeNew2004_v1.3_7.1_5A_USA_IL_CHICAGO-OHARE.csv
src/pymgrid/data/load/RefBldgPrimarySchoolNew2004_v1.3_7.1_2A_USA_TX_HOUSTON.csv
src/pymgrid/data/load/__init__.py
src/pymgrid/data/pv/Houston_722430TYA.csv
src/pymgrid/data/pv/Minneapolis_726580TYA.csv
src/pymgrid/data/pv/NewYork_744860TYA.csv
src/python_microgrid.egg-info/PKG-INFO
src/python_microgrid.egg-info/SOURCES.txt
src/python_microgrid.egg-info/dependency_links.txt
src/python_microgrid.egg-info/requires.txt
src/python_microgrid.egg-info/top_level.txt
