Metadata-Version: 2.1
Name: python-microgrid
Version: 1.4.1
Summary: A simulator for tertiary control of electrical microgrids
Download-URL: https://github.com/ahalev/python-microgrid/archive/refs/tags/v1.4.1.tar.gz
Maintainer: Avishai Halev
Maintainer-email: avishaihalev@gmail.com
License: GNU LGPL 3.0
Project-URL: Source Code, https://github.com/ahalev/python-microgrid
Project-URL: Documentation, https://python-microgrid.readthedocs.io/
Requires-Python: >=3.6
Provides-Extra: genset_mpc
Provides-Extra: dev
Provides-Extra: rtd
Provides-Extra: all
License-File: LICENSE
